task3_challenge/clktick.sv
module clktick #(
	parameter WIDTH = 16
)(
  // interface signals
  input  logic             clk,      // clock 
  input  logic             rst,      // reset
  input  logic             en,       // enable signal
  input  logic [WIDTH-1:0] N,     	 // clock divided by N+1
  output logic  		       tick      // tick output
);

logic [WIDTH-1:0] count;

//my laptop needs 24cycles

always_ff @ (posedge clk) begin
    if (rst) begin
        tick <= 1'b0;
        count <= N;  
        end
    else if (en) begin
	    if (count == 0) begin
		    tick <= 1'b1;
		    count <= N;
	        end
	    else begin
		    tick <= 1'b0;
		    count <= count - 1'b1;
	    end
    end
end
endmodule

task3/clktick.vcd
$version Generated by VerilatedVcd $end
$date Thu Nov  3 20:52:07 2022 $end
$timescale 1ps $end

 $scope module TOP $end
  $var wire 16 & N [15:0] $end
  $var wire  1 # clk $end
  $var wire  1 % en $end
  $var wire  1 $ rst $end
  $var wire  1 ' tick $end
  $scope module clktick $end
   $var wire 16 & N [15:0] $end
   $var wire 32 ) WIDTH [31:0] $end
   $var wire  1 # clk $end
   $var wire 16 ( count [15:0] $end
   $var wire  1 % en $end
   $var wire  1 $ rst $end
   $var wire  1 ' tick $end
  $upscope $end
 $upscope $end
$enddefinitions $end


#0
1#
0$
0%
b0000000000010001 &
0'
b0000000000000000 (
b00000000000000000000000000010000 )
#1
0#
#2
1#
1$
#3
0#
#4
1#
b0000000000010001 (
#5
0#
#6
1#
0$
#7
0#
#8
1#
1%
#9
0#
#10
1#
b0000000000010000 (
#11
0#
#12
1#
b0000000000001111 (
#13
0#
#14
1#
b0000000000001110 (
#15
0#
#16
1#
b0000000000001101 (
#17
0#
#18
1#
b0000000000001100 (
#19
0#
#20
1#
b0000000000001011 (
#21
0#
#22
1#
b0000000000001010 (
#23
0#
#24
1#
b0000000000001001 (
#25
0#
#26
1#
b0000000000001000 (
#27
0#
#28
1#
b0000000000000111 (
#29
0#
#30
1#
b0000000000000110 (
#31
0#
#32
1#
b0000000000000101 (
#33
0#
#34
1#
b0000000000000100 (
#35
0#
#36
1#
b0000000000000011 (
#37
0#
#38
1#
b0000000000000010 (
#39
0#
#40
1#
b0000000000000001 (
#41
0#
#42
1#
b0000000000000000 (
#43
0#
#44
1#
1'
b0000000000010001 (
#45
0#
#46
1#
0'
b0000000000010000 (
#47
0#
#48
1#
b0000000000001111 (
#49
0#
#50
1#
b0000000000001110 (
#51
0#
#52
1#
b0000000000001101 (
#53
0#
#54
1#
b0000000000001100 (
#55
0#
#56
1#
b0000000000001011 (
#57
0#
#58
1#
b0000000000001010 (
#59
0#
#60
1#
b0000000000001001 (
#61
0#
#62
1#
b0000000000001000 (
#63
0#
#64
1#
b0000000000000111 (
#65
0#
#66
1#
b0000000000000110 (
#67
0#
#68
1#
b0000000000000101 (
#69
0#
#70
1#
b0000000000000100 (
#71
0#
#72
1#
b0000000000000011 (
#73
0#
#74
1#
b0000000000000010 (
#75
0#
#76
1#
b0000000000000001 (
#77
0#
#78
1#
b0000000000000000 (
#79
0#
#80
1#
1'
b0000000000010001 (
#81
0#
#82
1#
0'
b0000000000010000 (
#83
0#
#84
1#
b0000000000001111 (
#85
0#
#86
1#
b0000000000001110 (
#87
0#
#88
1#
b0000000000001101 (
#89
0#
#90
1#
b0000000000001100 (
#91
0#
#92
1#
b0000000000001011 (
#93
0#
#94
1#
b0000000000001010 (
#95
0#
#96
1#
b0000000000001001 (
#97
0#
#98
1#
b0000000000001000 (
#99
0#
#100
1#
b0000000000000111 (
#101
0#
#102
1#
b0000000000000110 (
#103
0#
#104
1#
b0000000000000101 (
#105
0#
#106
1#
b0000000000000100 (
#107
0#
#108
1#
b0000000000000011 (
#109
0#
#110
1#
b0000000000000010 (
#111
0#
#112
1#
b0000000000000001 (
#113
0#
#114
1#
b0000000000000000 (
#115
0#
#116
1#
1'
b0000000000010001 (
#117
0#
#118
1#
0'
b0000000000010000 (
#119
0#
#120
1#
b0000000000001111 (
#121
0#
#122
1#
b0000000000001110 (
#123
0#
#124
1#
b0000000000001101 (
#125
0#
#126
1#
b0000000000001100 (
#127
0#
#128
1#
b0000000000001011 (
#129
0#
#130
1#
b0000000000001010 (
#131
0#
#132
1#
b0000000000001001 (
#133
0#
#134
1#
b0000000000001000 (
#135
0#
#136
1#
b0000000000000111 (
#137
0#
#138
1#
b0000000000000110 (
#139
0#
#140
1#
b0000000000000101 (
#141
0#
#142
1#
b0000000000000100 (
#143
0#
#144
1#
b0000000000000011 (
#145
0#
#146
1#
b0000000000000010 (
#147
0#
#148
1#
b0000000000000001 (
#149
0#
#150
1#
b0000000000000000 (
#151
0#
#152
1#
1'
b0000000000010001 (
#153
0#
#154
1#
0'
b0000000000010000 (
#155
0#
#156
1#
b0000000000001111 (
#157
0#
#158
1#
b0000000000001110 (
#159
0#
#160
1#
b0000000000001101 (
#161
0#
#162
1#
b0000000000001100 (
#163
0#
#164
1#
b0000000000001011 (
#165
0#
#166
1#
b0000000000001010 (
#167
0#
#168
1#
b0000000000001001 (
#169
0#
#170
1#
b0000000000001000 (
#171
0#
#172
1#
b0000000000000111 (
#173
0#
#174
1#
b0000000000000110 (
#175
0#
#176
1#
b0000000000000101 (
#177
0#
#178
1#
b0000000000000100 (
#179
0#
#180
1#
b0000000000000011 (
#181
0#
#182
1#
b0000000000000010 (
#183
0#
#184
1#
b0000000000000001 (
#185
0#
#186
1#
b0000000000000000 (
#187
0#
#188
1#
1'
b0000000000010001 (
#189
0#
#190
1#
0'
b0000000000010000 (
#191
0#
#192
1#
b0000000000001111 (
#193
0#
#194
1#
b0000000000001110 (
#195
0#
#196
1#
b0000000000001101 (
#197
0#
#198
1#
b0000000000001100 (
#199
0#
#200
1#
b0000000000001011 (
#201
0#
#202
1#
b0000000000001010 (
#203
0#
#204
1#
b0000000000001001 (
#205
0#
#206
1#
b0000000000001000 (
#207
0#
#208
1#
b0000000000000111 (
#209
0#
#210
1#
b0000000000000110 (
#211
0#
#212
1#
b0000000000000101 (
#213
0#
#214
1#
b0000000000000100 (
#215
0#
#216
1#
b0000000000000011 (
#217
0#
#218
1#
b0000000000000010 (
#219
0#
#220
1#
b0000000000000001 (
#221
0#
#222
1#
b0000000000000000 (
#223
0#
#224
1#
1'
b0000000000010001 (
#225
0#
#226
1#
0'
b0000000000010000 (
#227
0#
#228
1#
b0000000000001111 (
#229
0#
#230
1#
b0000000000001110 (
#231
0#
#232
1#
b0000000000001101 (
#233
0#
#234
1#
b0000000000001100 (
#235
0#
#236
1#
b0000000000001011 (
#237
0#
#238
1#
b0000000000001010 (
#239
0#
#240
1#
b0000000000001001 (
#241
0#
#242
1#
b0000000000001000 (
#243
0#
#244
1#
b0000000000000111 (
#245
0#
#246
1#
b0000000000000110 (
#247
0#
#248
1#
b0000000000000101 (
#249
0#
#250
1#
b0000000000000100 (
#251
0#
#252
1#
b0000000000000011 (
#253
0#
#254
1#
b0000000000000010 (
#255
0#
#256
1#
b0000000000000001 (
#257
0#
#258
1#
b0000000000000000 (
#259
0#
#260
1#
1'
b0000000000010001 (
#261
0#
#262
1#
0'
b0000000000010000 (
#263
0#
#264
1#
b0000000000001111 (
#265
0#
#266
1#
b0000000000001110 (
#267
0#
#268
1#
b0000000000001101 (
#269
0#
#270
1#
b0000000000001100 (
#271
0#
#272
1#
b0000000000001011 (
#273
0#
#274
1#
b0000000000001010 (
#275
0#
#276
1#
b0000000000001001 (
#277
0#
#278
1#
b0000000000001000 (
#279
0#
#280
1#
b0000000000000111 (
#281
0#
#282
1#
b0000000000000110 (
#283
0#
#284
1#
b0000000000000101 (
#285
0#
#286
1#
b0000000000000100 (
#287
0#
#288
1#
b0000000000000011 (
#289
0#
#290
1#
b0000000000000010 (
#291
0#
#292
1#
b0000000000000001 (
#293
0#
#294
1#
b0000000000000000 (
#295
0#
#296
1#
1'
b0000000000010001 (
#297
0#
#298
1#
0'
b0000000000010000 (
#299
0#
#300
1#
b0000000000001111 (
#301
0#
#302
1#
b0000000000001110 (
#303
0#
#304
1#
b0000000000001101 (
#305
0#
#306
1#
b0000000000001100 (
#307
0#
#308
1#
b0000000000001011 (
#309
0#
#310
1#
b0000000000001010 (
#311
0#
#312
1#
b0000000000001001 (
#313
0#
#314
1#
b0000000000001000 (
#315
0#
#316
1#
b0000000000000111 (
#317
0#
#318
1#
b0000000000000110 (
#319
0#
#320
1#
b0000000000000101 (
#321
0#
#322
1#
b0000000000000100 (
#323
0#
#324
1#
b0000000000000011 (
#325
0#
#326
1#
b0000000000000010 (
#327
0#
#328
1#
b0000000000000001 (
#329
0#
#330
1#
b0000000000000000 (
#331
0#
#332
1#
1'
b0000000000010001 (
#333
0#
#334
1#
0'
b0000000000010000 (
#335
0#
#336
1#
b0000000000001111 (
#337
0#
#338
1#
b0000000000001110 (
#339
0#
#340
1#
b0000000000001101 (
#341
0#
#342
1#
b0000000000001100 (
#343
0#
#344
1#
b0000000000001011 (
#345
0#
#346
1#
b0000000000001010 (
#347
0#
#348
1#
b0000000000001001 (
#349
0#
#350
1#
b0000000000001000 (
#351
0#
#352
1#
b0000000000000111 (
#353
0#
#354
1#
b0000000000000110 (
#355
0#
#356
1#
b0000000000000101 (
#357
0#
#358
1#
b0000000000000100 (
#359
0#
#360
1#
b0000000000000011 (
#361
0#
#362
1#
b0000000000000010 (
#363
0#
#364
1#
b0000000000000001 (
#365
0#
#366
1#
b0000000000000000 (
#367
0#
#368
1#
1'
b0000000000010001 (
#369
0#
#370
1#
0'
b0000000000010000 (
#371
0#
#372
1#
b0000000000001111 (
#373
0#
#374
1#
b0000000000001110 (
#375
0#
#376
1#
b0000000000001101 (
#377
0#
#378
1#
b0000000000001100 (
#379
0#
#380
1#
b0000000000001011 (
#381
0#
#382
1#
b0000000000001010 (
#383
0#
#384
1#
b0000000000001001 (
#385
0#
#386
1#
b0000000000001000 (
#387
0#
#388
1#
b0000000000000111 (
#389
0#
#390
1#
b0000000000000110 (
#391
0#
#392
1#
b0000000000000101 (
#393
0#
#394
1#
b0000000000000100 (
#395
0#
#396
1#
b0000000000000011 (
#397
0#
#398
1#
b0000000000000010 (
#399
0#
#400
1#
b0000000000000001 (
#401
0#
#402
1#
b0000000000000000 (
#403
0#
#404
1#
1'
b0000000000010001 (
#405
0#
#406
1#
0'
b0000000000010000 (
#407
0#
#408
1#
b0000000000001111 (
#409
0#
#410
1#
b0000000000001110 (
#411
0#
#412
1#
b0000000000001101 (
#413
0#
#414
1#
b0000000000001100 (
#415
0#
#416
1#
b0000000000001011 (
#417
0#
#418
1#
b0000000000001010 (
#419
0#
#420
1#
b0000000000001001 (
#421
0#
#422
1#
b0000000000001000 (
#423
0#
#424
1#
b0000000000000111 (
#425
0#
#426
1#
b0000000000000110 (
#427
0#
#428
1#
b0000000000000101 (
#429
0#
#430
1#
b0000000000000100 (
#431
0#
#432
1#
b0000000000000011 (
#433
0#
#434
1#
b0000000000000010 (
#435
0#
#436
1#
b0000000000000001 (
#437
0#
#438
1#
b0000000000000000 (
#439
0#
#440
1#
1'
b0000000000010001 (
#441
0#
#442
1#
0'
b0000000000010000 (
#443
0#
#444
1#
b0000000000001111 (
#445
0#
#446
1#
b0000000000001110 (
#447
0#
#448
1#
b0000000000001101 (
#449
0#
#450
1#
b0000000000001100 (
#451
0#
#452
1#
b0000000000001011 (
#453
0#
#454
1#
b0000000000001010 (
#455
0#
#456
1#
b0000000000001001 (
#457
0#
#458
1#
b0000000000001000 (
#459
0#
#460
1#
b0000000000000111 (
#461
0#
#462
1#
b0000000000000110 (
#463
0#
#464
1#
b0000000000000101 (
#465
0#
#466
1#
b0000000000000100 (
#467
0#
#468
1#
b0000000000000011 (
#469
0#
#470
1#
b0000000000000010 (
#471
0#
#472
1#
b0000000000000001 (
#473
0#
#474
1#
b0000000000000000 (
#475
0#
#476
1#
1'
b0000000000010001 (
#477
0#
#478
1#
0'
b0000000000010000 (
#479
0#
#480
1#
b0000000000001111 (
#481
0#
#482
1#
b0000000000001110 (
#483
0#
#484
1#
b0000000000001101 (
#485
0#
#486
1#
b0000000000001100 (
#487
0#
#488
1#
b0000000000001011 (
#489
0#
#490
1#
b0000000000001010 (
#491
0#
#492
1#
b0000000000001001 (
#493
0#
#494
1#
b0000000000001000 (
#495
0#
#496
1#
b0000000000000111 (
#497
0#
#498
1#
b0000000000000110 (
#499
0#
#500
1#
b0000000000000101 (
#501
0#
#502
1#
b0000000000000100 (
#503
0#
#504
1#
b0000000000000011 (
#505
0#
#506
1#
b0000000000000010 (
#507
0#
#508
1#
b0000000000000001 (
#509
0#
#510
1#
b0000000000000000 (
#511
0#
#512
1#
1'
b0000000000010001 (
#513
0#
#514
1#
0'
b0000000000010000 (
#515
0#
#516
1#
b0000000000001111 (
#517
0#
#518
1#
b0000000000001110 (
#519
0#
#520
1#
b0000000000001101 (
#521
0#
#522
1#
b0000000000001100 (
#523
0#
#524
1#
b0000000000001011 (
#525
0#
#526
1#
b0000000000001010 (
#527
0#
#528
1#
b0000000000001001 (
#529
0#
#530
1#
b0000000000001000 (
#531
0#
#532
1#
b0000000000000111 (
#533
0#
#534
1#
b0000000000000110 (
#535
0#
#536
1#
b0000000000000101 (
#537
0#
#538
1#
b0000000000000100 (
#539
0#
#540
1#
b0000000000000011 (
#541
0#
#542
1#
b0000000000000010 (
#543
0#
#544
1#
b0000000000000001 (
#545
0#
#546
1#
b0000000000000000 (
#547
0#
#548
1#
1'
b0000000000010001 (
#549
0#
#550
1#
0'
b0000000000010000 (
#551
0#
#552
1#
b0000000000001111 (
#553
0#
#554
1#
b0000000000001110 (
#555
0#
#556
1#
b0000000000001101 (
#557
0#
#558
1#
b0000000000001100 (
#559
0#
#560
1#
b0000000000001011 (
#561
0#
#562
1#
b0000000000001010 (
#563
0#
#564
1#
b0000000000001001 (
#565
0#
#566
1#
b0000000000001000 (
#567
0#
#568
1#
b0000000000000111 (
#569
0#
#570
1#
b0000000000000110 (
#571
0#
#572
1#
b0000000000000101 (
#573
0#
#574
1#
b0000000000000100 (
#575
0#
#576
1#
b0000000000000011 (
#577
0#
#578
1#
b0000000000000010 (
#579
0#
#580
1#
b0000000000000001 (
#581
0#
#582
1#
b0000000000000000 (
#583
0#
#584
1#
1'
b0000000000010001 (
#585
0#
#586
1#
0'
b0000000000010000 (
#587
0#
#588
1#
b0000000000001111 (
#589
0#
#590
1#
b0000000000001110 (
#591
0#
#592
1#
b0000000000001101 (
#593
0#
#594
1#
b0000000000001100 (
#595
0#
#596
1#
b0000000000001011 (
#597
0#
#598
1#
b0000000000001010 (
#599
0#
#600
1#
b0000000000001001 (
#601
0#
#602
1#
b0000000000001000 (
#603
0#
#604
1#
b0000000000000111 (
#605
0#
#606
1#
b0000000000000110 (
#607
0#
#608
1#
b0000000000000101 (
#609
0#
#610
1#
b0000000000000100 (
#611
0#
#612
1#
b0000000000000011 (
#613
0#
#614
1#
b0000000000000010 (
#615
0#
#616
1#
b0000000000000001 (
#617
0#
#618
1#
b0000000000000000 (
#619
0#
#620
1#
1'
b0000000000010001 (
#621
0#
#622
1#
0'
b0000000000010000 (
#623
0#
#624
1#
b0000000000001111 (
#625
0#
#626
1#
b0000000000001110 (
#627
0#
#628
1#
b0000000000001101 (
#629
0#
#630
1#
b0000000000001100 (
#631
0#
#632
1#
b0000000000001011 (
#633
0#
#634
1#
b0000000000001010 (
#635
0#
#636
1#
b0000000000001001 (
#637
0#
#638
1#
b0000000000001000 (
#639
0#
#640
1#
b0000000000000111 (
#641
0#
#642
1#
b0000000000000110 (
#643
0#
#644
1#
b0000000000000101 (
#645
0#
#646
1#
b0000000000000100 (
#647
0#
#648
1#
b0000000000000011 (
#649
0#
#650
1#
b0000000000000010 (
#651
0#
#652
1#
b0000000000000001 (
#653
0#
#654
1#
b0000000000000000 (
#655
0#
#656
1#
1'
b0000000000010001 (
#657
0#
#658
1#
0'
b0000000000010000 (
#659
0#
#660
1#
b0000000000001111 (
#661
0#
#662
1#
b0000000000001110 (
#663
0#
#664
1#
b0000000000001101 (
#665
0#
#666
1#
b0000000000001100 (
#667
0#
#668
1#
b0000000000001011 (
#669
0#
#670
1#
b0000000000001010 (
#671
0#
#672
1#
b0000000000001001 (
#673
0#
#674
1#
b0000000000001000 (
#675
0#
#676
1#
b0000000000000111 (
#677
0#
#678
1#
b0000000000000110 (
#679
0#
#680
1#
b0000000000000101 (
#681
0#
#682
1#
b0000000000000100 (
#683
0#
#684
1#
b0000000000000011 (
#685
0#
#686
1#
b0000000000000010 (
#687
0#
#688
1#
b0000000000000001 (
#689
0#
#690
1#
b0000000000000000 (
#691
0#
#692
1#
1'
b0000000000010001 (
#693
0#
#694
1#
0'
b0000000000010000 (
#695
0#
#696
1#
b0000000000001111 (
#697
0#
#698
1#
b0000000000001110 (
#699
0#
#700
1#
b0000000000001101 (
#701
0#
#702
1#
b0000000000001100 (
#703
0#
#704
1#
b0000000000001011 (
#705
0#
#706
1#
b0000000000001010 (
#707
0#
#708
1#
b0000000000001001 (
#709
0#
#710
1#
b0000000000001000 (
#711
0#
#712
1#
b0000000000000111 (
#713
0#
#714
1#
b0000000000000110 (
#715
0#
#716
1#
b0000000000000101 (
#717
0#
#718
1#
b0000000000000100 (
#719
0#
#720
1#
b0000000000000011 (
#721
0#
#722
1#
b0000000000000010 (
#723
0#
#724
1#
b0000000000000001 (
#725
0#
#726
1#
b0000000000000000 (
#727
0#
#728
1#
1'
b0000000000010001 (
#729
0#
#730
1#
0'
b0000000000010000 (
#731
0#
#732
1#
b0000000000001111 (
#733
0#
#734
1#
b0000000000001110 (
#735
0#
#736
1#
b0000000000001101 (
#737
0#
#738
1#
b0000000000001100 (
#739
0#
#740
1#
b0000000000001011 (
#741
0#
#742
1#
b0000000000001010 (
#743
0#
#744
1#
b0000000000001001 (
#745
0#
#746
1#
b0000000000001000 (
#747
0#
#748
1#
b0000000000000111 (
#749
0#
#750
1#
b0000000000000110 (
#751
0#
#752
1#
b0000000000000101 (
#753
0#
#754
1#
b0000000000000100 (
#755
0#
#756
1#
b0000000000000011 (
#757
0#
#758
1#
b0000000000000010 (
#759
0#
#760
1#
b0000000000000001 (
#761
0#
#762
1#
b0000000000000000 (
#763
0#
#764
1#
1'
b0000000000010001 (
#765
0#
#766
1#
0'
b0000000000010000 (
#767
0#
#768
1#
b0000000000001111 (
#769
0#
#770
1#
b0000000000001110 (
#771
0#
#772
1#
b0000000000001101 (
#773
0#
#774
1#
b0000000000001100 (
#775
0#
#776
1#
b0000000000001011 (
#777
0#
#778
1#
b0000000000001010 (
#779
0#
#780
1#
b0000000000001001 (
#781
0#
#782
1#
b0000000000001000 (
#783
0#
#784
1#
b0000000000000111 (
#785
0#
#786
1#
b0000000000000110 (
#787
0#
#788
1#
b0000000000000101 (
#789
0#
#790
1#
b0000000000000100 (
#791
0#
#792
1#
b0000000000000011 (
#793
0#
#794
1#
b0000000000000010 (
#795
0#
#796
1#
b0000000000000001 (
#797
0#
#798
1#
b0000000000000000 (
#799
0#
#800
1#
1'
b0000000000010001 (
#801
0#
#802
1#
0'
b0000000000010000 (
#803
0#
#804
1#
b0000000000001111 (
#805
0#
#806
1#
b0000000000001110 (
#807
0#
#808
1#
b0000000000001101 (
#809
0#
#810
1#
b0000000000001100 (
#811
0#
#812
1#
b0000000000001011 (
#813
0#
#814
1#
b0000000000001010 (
#815
0#
#816
1#
b0000000000001001 (
#817
0#
#818
1#
b0000000000001000 (
#819
0#
#820
1#
b0000000000000111 (
#821
0#
#822
1#
b0000000000000110 (
#823
0#
#824
1#
b0000000000000101 (
#825
0#
#826
1#
b0000000000000100 (
#827
0#
#828
1#
b0000000000000011 (
#829
0#
#830
1#
b0000000000000010 (
#831
0#
#832
1#
b0000000000000001 (
#833
0#
#834
1#
b0000000000000000 (
#835
0#
#836
1#
1'
b0000000000010001 (
#837
0#
#838
1#
0'
b0000000000010000 (
#839
0#
#840
1#
b0000000000001111 (
#841
0#
#842
1#
b0000000000001110 (
#843
0#
#844
1#
b0000000000001101 (
#845
0#
#846
1#
b0000000000001100 (
#847
0#
#848
1#
b0000000000001011 (
#849
0#
#850
1#
b0000000000001010 (
#851
0#
#852
1#
b0000000000001001 (
#853
0#
#854
1#
b0000000000001000 (
#855
0#
#856
1#
b0000000000000111 (
#857
0#
#858
1#
b0000000000000110 (
#859
0#
#860
1#
b0000000000000101 (
#861
0#
#862
1#
b0000000000000100 (
#863
0#
#864
1#
b0000000000000011 (
#865
0#
#866
1#
b0000000000000010 (
#867
0#
#868
1#
b0000000000000001 (
#869
0#
#870
1#
b0000000000000000 (
#871
0#
#872
1#
1'
b0000000000010001 (
#873
0#
#874
1#
0'
b0000000000010000 (
#875
0#
#876
1#
b0000000000001111 (
#877
0#
#878
1#
b0000000000001110 (
#879
0#
#880
1#
b0000000000001101 (
#881
0#
#882
1#
b0000000000001100 (
#883
0#
#884
1#
b0000000000001011 (
#885
0#
#886
1#
b0000000000001010 (
#887
0#
#888
1#
b0000000000001001 (
#889
0#
#890
1#
b0000000000001000 (
#891
0#
#892
1#
b0000000000000111 (
#893
0#
#894
1#
b0000000000000110 (
#895
0#
#896
1#
b0000000000000101 (
#897
0#
#898
1#
b0000000000000100 (
#899
0#
#900
1#
b0000000000000011 (
#901
0#
#902
1#
b0000000000000010 (
#903
0#
#904
1#
b0000000000000001 (
#905
0#
#906
1#
b0000000000000000 (
#907
0#
#908
1#
1'
b0000000000010001 (
#909
0#
#910
1#
0'
b0000000000010000 (
#911
0#
#912
1#
b0000000000001111 (
#913
0#
#914
1#
b0000000000001110 (
#915
0#
#916
1#
b0000000000001101 (
#917
0#
#918
1#
b0000000000001100 (
#919
0#
#920
1#
b0000000000001011 (
#921
0#
#922
1#
b0000000000001010 (
#923
0#
#924
1#
b0000000000001001 (
#925
0#
#926
1#
b0000000000001000 (
#927
0#
#928
1#
b0000000000000111 (
#929
0#
#930
1#
b0000000000000110 (
#931
0#
#932
1#
b0000000000000101 (
#933
0#
#934
1#
b0000000000000100 (
#935
0#
#936
1#
b0000000000000011 (
#937
0#
#938
1#
b0000000000000010 (
#939
0#
#940
1#
b0000000000000001 (
#941
0#
#942
1#
b0000000000000000 (
#943
0#
#944
1#
1'
b0000000000010001 (
#945
0#
#946
1#
0'
b0000000000010000 (
#947
0#
#948
1#
b0000000000001111 (
#949
0#
#950
1#
b0000000000001110 (
#951
0#
#952
1#
b0000000000001101 (
#953
0#
#954
1#
b0000000000001100 (
#955
0#
#956
1#
b0000000000001011 (
#957
0#
#958
1#
b0000000000001010 (
#959
0#
#960
1#
b0000000000001001 (
#961
0#
#962
1#
b0000000000001000 (
#963
0#
#964
1#
b0000000000000111 (
#965
0#
#966
1#
b0000000000000110 (
#967
0#
#968
1#
b0000000000000101 (
#969
0#
#970
1#
b0000000000000100 (
#971
0#
#972
1#
b0000000000000011 (
#973
0#
#974
1#
b0000000000000010 (
#975
0#
#976
1#
b0000000000000001 (
#977
0#
#978
1#
b0000000000000000 (
#979
0#
#980
1#
1'
b0000000000010001 (
#981
0#
#982
1#
0'
b0000000000010000 (
#983
0#
#984
1#
b0000000000001111 (
#985
0#
#986
1#
b0000000000001110 (
#987
0#
#988
1#
b0000000000001101 (
#989
0#
#990
1#
b0000000000001100 (
#991
0#
#992
1#
b0000000000001011 (
#993
0#
#994
1#
b0000000000001010 (
#995
0#
#996
1#
b0000000000001001 (
#997
0#
#998
1#
b0000000000001000 (
#999
0#
#1000
1#
b0000000000000111 (
#1001
0#
#1002
1#
b0000000000000110 (
#1003
0#
#1004
1#
b0000000000000101 (
#1005
0#
#1006
1#
b0000000000000100 (
#1007
0#
#1008
1#
b0000000000000011 (
#1009
0#
#1010
1#
b0000000000000010 (
#1011
0#
#1012
1#
b0000000000000001 (
#1013
0#
#1014
1#
b0000000000000000 (
#1015
0#
#1016
1#
1'
b0000000000010001 (
#1017
0#
#1018
1#
0'
b0000000000010000 (
#1019
0#
#1020
1#
b0000000000001111 (
#1021
0#
#1022
1#
b0000000000001110 (
#1023
0#
#1024
1#
b0000000000001101 (
#1025
0#
#1026
1#
b0000000000001100 (
#1027
0#
#1028
1#
b0000000000001011 (
#1029
0#
#1030
1#
b0000000000001010 (
#1031
0#
#1032
1#
b0000000000001001 (
#1033
0#
#1034
1#
b0000000000001000 (
#1035
0#
#1036
1#
b0000000000000111 (
#1037
0#
#1038
1#
b0000000000000110 (
#1039
0#
#1040
1#
b0000000000000101 (
#1041
0#
#1042
1#
b0000000000000100 (
#1043
0#
#1044
1#
b0000000000000011 (
#1045
0#
#1046
1#
b0000000000000010 (
#1047
0#
#1048
1#
b0000000000000001 (
#1049
0#
#1050
1#
b0000000000000000 (
#1051
0#
#1052
1#
1'
b0000000000010001 (
#1053
0#
#1054
1#
0'
b0000000000010000 (
#1055
0#
#1056
1#
b0000000000001111 (
#1057
0#
#1058
1#
b0000000000001110 (
#1059
0#
#1060
1#
b0000000000001101 (
#1061
0#
#1062
1#
b0000000000001100 (
#1063
0#
#1064
1#
b0000000000001011 (
#1065
0#
#1066
1#
b0000000000001010 (
#1067
0#
#1068
1#
b0000000000001001 (
#1069
0#
#1070
1#
b0000000000001000 (
#1071
0#
#1072
1#
b0000000000000111 (
#1073
0#
#1074
1#
b0000000000000110 (
#1075
0#
#1076
1#
b0000000000000101 (
#1077
0#
#1078
1#
b0000000000000100 (
#1079
0#
#1080
1#
b0000000000000011 (
#1081
0#
#1082
1#
b0000000000000010 (
#1083
0#
#1084
1#
b0000000000000001 (
#1085
0#
#1086
1#
b0000000000000000 (
#1087
0#
#1088
1#
1'
b0000000000010001 (
#1089
0#
#1090
1#
0'
b0000000000010000 (
#1091
0#
#1092
1#
b0000000000001111 (
#1093
0#
#1094
1#
b0000000000001110 (
#1095
0#
#1096
1#
b0000000000001101 (
#1097
0#
#1098
1#
b0000000000001100 (
#1099
0#
#1100
1#
b0000000000001011 (
#1101
0#
#1102
1#
b0000000000001010 (
#1103
0#
#1104
1#
b0000000000001001 (
#1105
0#
#1106
1#
b0000000000001000 (
#1107
0#
#1108
1#
b0000000000000111 (
#1109
0#
#1110
1#
b0000000000000110 (
#1111
0#
#1112
1#
b0000000000000101 (
#1113
0#
#1114
1#
b0000000000000100 (
#1115
0#
#1116
1#
b0000000000000011 (
#1117
0#
#1118
1#
b0000000000000010 (
#1119
0#
#1120
1#
b0000000000000001 (
#1121
0#
#1122
1#
b0000000000000000 (
#1123
0#
#1124
1#
1'
b0000000000010001 (
#1125
0#
#1126
1#
0'
b0000000000010000 (
#1127
0#
#1128
1#
b0000000000001111 (
#1129
0#
#1130
1#
b0000000000001110 (
#1131
0#
#1132
1#
b0000000000001101 (
#1133
0#
#1134
1#
b0000000000001100 (
#1135
0#
#1136
1#
b0000000000001011 (
#1137
0#
#1138
1#
b0000000000001010 (
#1139
0#
#1140
1#
b0000000000001001 (
#1141
0#
#1142
1#
b0000000000001000 (
#1143
0#
#1144
1#
b0000000000000111 (
#1145
0#
#1146
1#
b0000000000000110 (
#1147
0#
#1148
1#
b0000000000000101 (
#1149
0#
#1150
1#
b0000000000000100 (
#1151
0#
#1152
1#
b0000000000000011 (
#1153
0#
#1154
1#
b0000000000000010 (
#1155
0#
#1156
1#
b0000000000000001 (
#1157
0#
#1158
1#
b0000000000000000 (
#1159
0#
#1160
1#
1'
b0000000000010001 (
#1161
0#
#1162
1#
0'
b0000000000010000 (
#1163
0#
#1164
1#
b0000000000001111 (
#1165
0#
#1166
1#
b0000000000001110 (
#1167
0#
#1168
1#
b0000000000001101 (
#1169
0#
#1170
1#
b0000000000001100 (
#1171
0#
#1172
1#
b0000000000001011 (
#1173
0#
#1174
1#
b0000000000001010 (
#1175
0#
#1176
1#
b0000000000001001 (
#1177
0#
#1178
1#
b0000000000001000 (
#1179
0#
#1180
1#
b0000000000000111 (
#1181
0#
#1182
1#
b0000000000000110 (
#1183
0#
#1184
1#
b0000000000000101 (
#1185
0#
#1186
1#
b0000000000000100 (
#1187
0#
#1188
1#
b0000000000000011 (
#1189
0#
#1190
1#
b0000000000000010 (
#1191
0#
#1192
1#
b0000000000000001 (
#1193
0#
#1194
1#
b0000000000000000 (
#1195
0#
#1196
1#
1'
b0000000000010001 (
#1197
0#
#1198
1#
0'
b0000000000010000 (
#1199
0#
#1200
1#
b0000000000001111 (
#1201
0#
#1202
1#
b0000000000001110 (
#1203
0#
#1204
1#
b0000000000001101 (
#1205
0#
#1206
1#
b0000000000001100 (
#1207
0#
#1208
1#
b0000000000001011 (
#1209
0#
#1210
1#
b0000000000001010 (
#1211
0#
#1212
1#
b0000000000001001 (
#1213
0#
#1214
1#
b0000000000001000 (
#1215
0#
#1216
1#
b0000000000000111 (
#1217
0#
#1218
1#
b0000000000000110 (
#1219
0#
#1220
1#
b0000000000000101 (
#1221
0#
#1222
1#
b0000000000000100 (
#1223
0#
#1224
1#
b0000000000000011 (
#1225
0#
#1226
1#
b0000000000000010 (
#1227
0#
#1228
1#
b0000000000000001 (
#1229
0#
#1230
1#
b0000000000000000 (
#1231
0#
#1232
1#
1'
b0000000000010001 (
#1233
0#
#1234
1#
0'
b0000000000010000 (
#1235
0#
#1236
1#
b0000000000001111 (
#1237
0#
#1238
1#
b0000000000001110 (
#1239
0#
#1240
1#
b0000000000001101 (
#1241
0#
#1242
1#
b0000000000001100 (
#1243
0#
#1244
1#
b0000000000001011 (
#1245
0#
#1246
1#
b0000000000001010 (
#1247
0#
#1248
1#
b0000000000001001 (
#1249
0#
#1250
1#
b0000000000001000 (
#1251
0#
#1252
1#
b0000000000000111 (
#1253
0#
#1254
1#
b0000000000000110 (
#1255
0#
#1256
1#
b0000000000000101 (
#1257
0#
#1258
1#
b0000000000000100 (
#1259
0#
#1260
1#
b0000000000000011 (
#1261
0#
#1262
1#
b0000000000000010 (
#1263
0#
