task4/lfsr.sv
module lfsr (
    input logic         clk,
    input logic         rst,
    input logic         en,

    output logic [6:0]  data_out
);

logic [7:1] sreg; //shift register

initial begin
    sreg[7:1] = 7'b0000001;
end

always_ff @(posedge clk) begin
    if(en) begin
        if (rst) begin
            sreg <= 7'b0;
        end
        else begin
            sreg[7] <= sreg[6];
            sreg[6] <= sreg[5];
            sreg[5] <= sreg[4];
            sreg[4] <= sreg[3];
            sreg[3] <= sreg[2];
            sreg[2] <= sreg[1];
            sreg[1] <= sreg[3] ^ sreg[7];
        end
    end
end

assign data_out [6:0] = sreg[7:1];

endmodule

task4/f1_fsm.sv
module f1_fsm(
    input logic             rst,
    input logic             en,
    input logic             clk,
    input logic             trigger,

    output logic [7:0]      data_out,
    output logic            cmd_seq,
    output logic            cmd_delay
);
//doesn't turn off check why

//typedef
typedef enum {S0, S1, S2, S3, S4, S5, S6, S7, S8} f1_state;
f1_state current_state, next_state;

//next state logic
always_comb begin
    if(en == 1'b1) begin
        case(current_state)
            S0:         next_state = S1;
            S1:         next_state = S2;
            S2:         next_state = S3;
            S3:         next_state = S4;
            S4:         next_state = S5;
            S5:         next_state = S6;
            S6:         next_state = S7;
            S7:         next_state = S8;
            S8:         next_state = S0;
            default     next_state = S0;
        endcase
    end
end



//cmd delay
always_comb begin
    if(current_state != S0) begin
        cmd_seq = 1'b1;
    end
    else begin
        cmd_seq = 1'b0;
    end
end





always_comb begin
    if (current_state == S8) begin
        cmd_delay = 1'b1;
    end
    else begin
        cmd_delay = 1'b0;
    end
end


//state transition
always_ff @(posedge clk) begin
    if (rst)    current_state <= S0;
    else if (trigger == 1'b1) begin
        current_state <= S1;
    end
    else if ((en == 1'b1) && (cmd_seq == 1'b1))begin
        current_state <= next_state;
    end
end

//output logic
always_comb begin
    if(en == 1'b1) begin
        case(current_state)
            S0:         data_out = 8'b0;
            S1:         data_out = 8'b1;
            S2:         data_out = 8'b11;
            S3:         data_out = 8'b111;
            S4:         data_out = 8'b1111;
            S5:         data_out = 8'b11111;
            S6:         data_out = 8'b111111;
            S7:         data_out = 8'b1111111;
            S8:         data_out = 8'b11111111;
            default     data_out = 8'b0;
        endcase
    end
end

endmodule

task4/delay.sv
module delay #(
	parameter WIDTH = 7    // no of bits in delay counter
)(
    input   logic               clk,        // clock signal
    input   logic               rst,        // reset signal
    input   logic               trigger,    // trigger input signal
    input   logic [WIDTH-1:0]   n,          // no of clock cycle delay
    output  logic               time_out    // output pulse signal
);
    // Declare counter
    logic [WIDTH-1:0]   count = {WIDTH{1'b0}};            // internal counter

    // Define our states
    typedef enum {IDLE, COUNTING, TIME_OUT, WAIT_LOW}  my_state;
    my_state current_state, next_state;

    // counter
    always_ff @(posedge clk)
        if (rst | trigger | count=={WIDTH{1'b0}}) count <= n - 1'b1;
        else                                count <= count - 1'b1;

    // state transition
    always_ff @(posedge clk)
        if (rst)    current_state <= IDLE;
        else        current_state <= next_state; 

    // next state logic
    always_comb
        case (current_state)
            IDLE:       if (trigger==1'b1)  next_state = COUNTING;
                        else    next_state = current_state;
            COUNTING:   if (count=={WIDTH{1'b0}}) next_state = TIME_OUT;
                        else    next_state = current_state;
            TIME_OUT:   if (trigger==1'b1)  next_state = WAIT_LOW;
                        else    next_state = IDLE;
            WAIT_LOW:   if (trigger==1'b0)  next_state = IDLE;
                        else    next_state = current_state;
            default: next_state = IDLE;
        endcase
    
    // output logic
    always_comb
        case (current_state)
            IDLE:       time_out = 1'b0;
            COUNTING:   time_out = 1'b0;
            TIME_OUT:   time_out = 1'b1;
            WAIT_LOW:   time_out = 1'b0;
            default:    time_out = 1'b0;
        endcase
    
    //always_comb begin
        //$display(trigger);
    //end
endmodule

task4/clktick.sv
module clktick #(
	//parameter WIDTH = 16
)(
  // interface signals
  input  logic             clk,      // clock 
  input  logic             rst,      // reset
  input  logic             en,       // enable signal
  input  logic [4:0] N,     	 // clock divided by N+1
  output logic  		       tick      // tick output
);

logic [4:0] count;

//my laptop needs 24cycles

always_ff @ (posedge clk) begin
    if (rst) begin
        tick <= 1'b0;
        count <= N;  
        end
    else if (en) begin
	    if (count == 0) begin
		    tick <= 1'b1;
		    count <= N;
	        end
	    else begin
		    tick <= 1'b0;
		    count <= count - 1'b1;
	    end
    end
end
endmodule

task4/top.sv
module top (
    input logic             rst,
    input logic             clk,
    input logic             trigger,
    input logic [7:0]       bin,

    output logic [11:0]     BCD,
    output logic [7:0]      data_out
);

logic cmd_seq;
logic cmd_delay;
logic tick;
logic time_out;
logic [6:0] k;



clktick clktick_block(
    .N (5'd14),
    .en (cmd_seq),
    .rst (rst),
    .clk (clk),
    .tick(tick)
);

delay delay_block(
    .n (k),
    .trigger (cmd_delay),
    .rst (rst),
    .clk (clk),
    .time_out (time_out)
);

f1_fsm f1_fsm_block(
    .rst(rst),
    .en(cmd_seq ? tick : time_out),
    .trigger (trigger),
    .clk(clk),
    .data_out(data_out),
    .cmd_seq (cmd_seq),
    .cmd_delay(cmd_delay)
);

lfsr lfsr_block(
    .clk (clk),
    .rst (1'b0),
    .en (1'b1),
    .data_out (k)
);

//bin2bcd bin2bcd_block(
//    .x (bin),
//    .BCD (BCD)
//);

endmodule

task4/top.vcd
$version Generated by VerilatedVcd $end
$date Fri Nov  4 11:56:13 2022 $end
$timescale 1ps $end

 $scope module TOP $end
  $var wire 12 4 BCD [11:0] $end
  $var wire  8 3 bin [7:0] $end
  $var wire  1 1 clk $end
  $var wire  8 5 data_out [7:0] $end
  $var wire  1 0 rst $end
  $var wire  1 2 trigger $end
  $scope module top $end
   $var wire 12 4 BCD [11:0] $end
   $var wire  8 3 bin [7:0] $end
   $var wire  1 1 clk $end
   $var wire  1 $ cmd_delay $end
   $var wire  1 # cmd_seq $end
   $var wire  8 5 data_out [7:0] $end
   $var wire  7 ' k [6:0] $end
   $var wire  1 0 rst $end
   $var wire  1 % tick $end
   $var wire  1 & time_out $end
   $var wire  1 2 trigger $end
   $scope module clktick_block $end
    $var wire  5 6 N [4:0] $end
    $var wire  1 1 clk $end
    $var wire  5 ( count [4:0] $end
    $var wire  1 # en $end
    $var wire  1 0 rst $end
    $var wire  1 % tick $end
   $upscope $end
   $scope module delay_block $end
    $var wire 32 7 WIDTH [31:0] $end
    $var wire  1 1 clk $end
    $var wire  7 ) count [6:0] $end
    $var wire 32 * current_state [31:0] $end
    $var wire  7 ' n [6:0] $end
    $var wire 32 + next_state [31:0] $end
    $var wire  1 0 rst $end
    $var wire  1 & time_out $end
    $var wire  1 $ trigger $end
   $upscope $end
   $scope module f1_fsm_block $end
    $var wire  1 1 clk $end
    $var wire  1 $ cmd_delay $end
    $var wire  1 # cmd_seq $end
    $var wire 32 - current_state [31:0] $end
    $var wire  8 5 data_out [7:0] $end
    $var wire  1 , en $end
    $var wire 32 . next_state [31:0] $end
    $var wire  1 0 rst $end
    $var wire  1 2 trigger $end
   $upscope $end
   $scope module lfsr_block $end
    $var wire  1 1 clk $end
    $var wire  7 ' data_out [6:0] $end
    $var wire  1 9 en $end
    $var wire  1 8 rst $end
    $var wire  7 / sreg [7:1] $end
   $upscope $end
  $upscope $end
 $upscope $end
$enddefinitions $end


#0
0#
0$
0%
0&
b0000000 '
b00000 (
b0000000 )
b00000000000000000000000000000000 *
b00000000000000000000000000000000 +
0,
b00000000000000000000000000000000 -
b00000000000000000000000000000000 .
b0000000 /
00
11
02
b00000000 3
b000000000000 4
b00000000 5
b01110 6
b00000000000000000000000000000111 7
08
19
#1
b0000001 '
b0000001 /
01
#2
b0000010 '
b0000010 /
10
11
#3
01
#4
b0000100 '
b01110 (
b0000001 )
b0000100 /
11
#5
01
#6
b0001001 '
b0000011 )
b0001001 /
00
11
#7
01
#8
b0010010 '
b0000010 )
b0010010 /
11
#9
01
#10
b0100100 '
b0000001 )
b0100100 /
11
#11
01
#12
b1001001 '
b0000000 )
b1001001 /
11
#13
01
#14
b0010011 '
b1001000 )
b0010011 /
11
#15
01
#16
b0100110 '
b1000111 )
b0100110 /
11
#17
01
#18
b1001101 '
b1000110 )
b1001101 /
11
#19
01
#20
b0011010 '
b1000101 )
b0011010 /
11
#21
01
#22
b0110100 '
b1000100 )
b0110100 /
11
#23
01
#24
b1101001 '
b1000011 )
b1101001 /
11
#25
01
#26
b1010011 '
b1000010 )
b1010011 /
11
#27
01
#28
b0100111 '
b1000001 )
b0100111 /
11
#29
01
#30
b1001111 '
b1000000 )
b1001111 /
11
#31
01
#32
b0011110 '
b0111111 )
b0011110 /
11
#33
01
#34
b0111101 '
b0111110 )
b0111101 /
11
#35
01
#36
b1111011 '
b0111101 )
b1111011 /
11
#37
01
#38
b1110111 '
b0111100 )
b1110111 /
11
#39
01
#40
b1101110 '
b0111011 )
b1101110 /
11
#41
01
#42
b1011100 '
b0111010 )
b1011100 /
11
#43
01
#44
b0111000 '
b0111001 )
b0111000 /
11
#45
01
#46
b1110000 '
b0111000 )
b1110000 /
11
#47
01
#48
b1100001 '
b0110111 )
b1100001 /
11
#49
01
#50
b1000011 '
b0110110 )
b1000011 /
11
#51
01
#52
b0000111 '
b0110101 )
b0000111 /
11
#53
01
#54
b0001111 '
b0110100 )
b0001111 /
11
#55
01
#56
b0011111 '
b0110011 )
b0011111 /
11
#57
01
#58
b0111111 '
b0110010 )
b0111111 /
11
12
#59
01
#60
1#
b1111111 '
b0110001 )
b00000000000000000000000000000001 -
b1111111 /
11
02
#61
01
#62
b1111110 '
b01101 (
b0110000 )
b1111110 /
11
#63
01
#64
b1111100 '
b01100 (
b0101111 )
b1111100 /
11
#65
01
#66
b1111000 '
b01011 (
b0101110 )
b1111000 /
11
#67
01
#68
b1110001 '
b01010 (
b0101101 )
b1110001 /
11
#69
01
#70
b1100011 '
b01001 (
b0101100 )
b1100011 /
11
#71
01
#72
b1000111 '
b01000 (
b0101011 )
b1000111 /
11
#73
01
#74
b0001110 '
b00111 (
b0101010 )
b0001110 /
11
#75
01
#76
b0011101 '
b00110 (
b0101001 )
b0011101 /
11
#77
01
#78
b0111011 '
b00101 (
b0101000 )
b0111011 /
11
#79
01
#80
b1110110 '
b00100 (
b0100111 )
b1110110 /
11
#81
01
#82
b1101100 '
b00011 (
b0100110 )
b1101100 /
11
#83
01
#84
b1011000 '
b00010 (
b0100101 )
b1011000 /
11
#85
01
#86
b0110001 '
b00001 (
b0100100 )
b0110001 /
11
#87
01
#88
b1100010 '
b00000 (
b0100011 )
b1100010 /
11
#89
01
#90
1%
b1000101 '
b01110 (
b0100010 )
1,
b00000000000000000000000000000010 .
b1000101 /
11
b00000001 5
#91
01
#92
0%
b0001010 '
b01101 (
b0100001 )
0,
b00000000000000000000000000000010 -
b0001010 /
11
#93
01
#94
b0010100 '
b01100 (
b0100000 )
b0010100 /
11
#95
01
#96
b0101001 '
b01011 (
b0011111 )
b0101001 /
11
#97
01
#98
b1010010 '
b01010 (
b0011110 )
b1010010 /
11
#99
01
#100
b0100101 '
b01001 (
b0011101 )
b0100101 /
11
#101
01
#102
b1001011 '
b01000 (
b0011100 )
b1001011 /
11
#103
01
#104
b0010111 '
b00111 (
b0011011 )
b0010111 /
11
#105
01
#106
b0101111 '
b00110 (
b0011010 )
b0101111 /
11
#107
01
#108
b1011111 '
b00101 (
b0011001 )
b1011111 /
11
#109
01
#110
b0111110 '
b00100 (
b0011000 )
b0111110 /
11
#111
01
#112
b1111101 '
b00011 (
b0010111 )
b1111101 /
11
#113
01
#114
b1111010 '
b00010 (
b0010110 )
b1111010 /
11
#115
01
#116
b1110101 '
b00001 (
b0010101 )
b1110101 /
11
#117
01
#118
b1101010 '
b00000 (
b0010100 )
b1101010 /
11
#119
01
#120
1%
b1010101 '
b01110 (
b0010011 )
1,
b00000000000000000000000000000011 .
b1010101 /
11
b00000011 5
#121
01
#122
0%
b0101010 '
b01101 (
b0010010 )
0,
b00000000000000000000000000000011 -
b0101010 /
11
#123
01
#124
b1010100 '
b01100 (
b0010001 )
b1010100 /
11
#125
01
#126
b0101000 '
b01011 (
b0010000 )
b0101000 /
11
#127
01
#128
b1010000 '
b01010 (
b0001111 )
b1010000 /
11
#129
01
#130
b0100001 '
b01001 (
b0001110 )
b0100001 /
11
#131
01
#132
b1000010 '
b01000 (
b0001101 )
b1000010 /
11
#133
01
#134
b0000101 '
b00111 (
b0001100 )
b0000101 /
11
#135
01
#136
b0001011 '
b00110 (
b0001011 )
b0001011 /
11
#137
01
#138
b0010110 '
b00101 (
b0001010 )
b0010110 /
11
#139
01
#140
b0101101 '
b00100 (
b0001001 )
b0101101 /
11
#141
01
#142
b1011011 '
b00011 (
b0001000 )
b1011011 /
11
#143
01
#144
b0110111 '
b00010 (
b0000111 )
b0110111 /
11
#145
01
#146
b1101111 '
b00001 (
b0000110 )
b1101111 /
11
#147
01
#148
b1011110 '
b00000 (
b0000101 )
b1011110 /
11
#149
01
#150
1%
b0111100 '
b01110 (
b0000100 )
1,
b00000000000000000000000000000100 .
b0111100 /
11
b00000111 5
#151
01
#152
0%
b1111001 '
b01101 (
b0000011 )
0,
b00000000000000000000000000000100 -
b1111001 /
11
#153
01
#154
b1110011 '
b01100 (
b0000010 )
b1110011 /
11
#155
01
#156
b1100111 '
b01011 (
b0000001 )
b1100111 /
11
#157
01
#158
b1001110 '
b01010 (
b0000000 )
b1001110 /
11
#159
01
#160
b0011100 '
b01001 (
b1001101 )
b0011100 /
11
#161
01
#162
b0111001 '
b01000 (
b1001100 )
b0111001 /
11
#163
01
#164
b1110010 '
b00111 (
b1001011 )
b1110010 /
11
#165
01
#166
b1100101 '
b00110 (
b1001010 )
b1100101 /
11
#167
01
#168
b1001010 '
b00101 (
b1001001 )
b1001010 /
11
#169
01
#170
b0010101 '
b00100 (
b1001000 )
b0010101 /
11
#171
01
#172
b0101011 '
b00011 (
b1000111 )
b0101011 /
11
#173
01
#174
b1010110 '
b00010 (
b1000110 )
b1010110 /
11
#175
01
#176
b0101100 '
b00001 (
b1000101 )
b0101100 /
11
#177
01
#178
b1011001 '
b00000 (
b1000100 )
b1011001 /
11
#179
01
#180
1%
b0110011 '
b01110 (
b1000011 )
1,
b00000000000000000000000000000101 .
b0110011 /
11
b00001111 5
#181
01
#182
0%
b1100110 '
b01101 (
b1000010 )
0,
b00000000000000000000000000000101 -
b1100110 /
11
#183
01
#184
b1001100 '
b01100 (
b1000001 )
b1001100 /
11
#185
01
#186
b0011000 '
b01011 (
b1000000 )
b0011000 /
11
#187
01
#188
b0110000 '
b01010 (
b0111111 )
b0110000 /
11
#189
01
#190
b1100000 '
b01001 (
b0111110 )
b1100000 /
11
#191
01
#192
b1000001 '
b01000 (
b0111101 )
b1000001 /
11
#193
01
#194
b0000011 '
b00111 (
b0111100 )
b0000011 /
11
#195
01
#196
b0000110 '
b00110 (
b0111011 )
b0000110 /
11
#197
01
#198
b0001101 '
b00101 (
b0111010 )
b0001101 /
11
#199
01
#200
b0011011 '
b00100 (
b0111001 )
b0011011 /
11
#201
01
#202
b0110110 '
b00011 (
b0111000 )
b0110110 /
11
#203
01
#204
b1101101 '
b00010 (
b0110111 )
b1101101 /
11
#205
01
#206
b1011010 '
b00001 (
b0110110 )
b1011010 /
11
#207
01
#208
b0110101 '
b00000 (
b0110101 )
b0110101 /
11
#209
01
#210
1%
b1101011 '
b01110 (
b0110100 )
1,
b00000000000000000000000000000110 .
b1101011 /
11
b00011111 5
#211
01
#212
0%
b1010111 '
b01101 (
b0110011 )
0,
b00000000000000000000000000000110 -
b1010111 /
11
#213
01
#214
b0101110 '
b01100 (
b0110010 )
b0101110 /
11
#215
01
#216
b1011101 '
b01011 (
b0110001 )
b1011101 /
11
#217
01
#218
b0111010 '
b01010 (
b0110000 )
b0111010 /
11
#219
01
#220
b1110100 '
b01001 (
b0101111 )
b1110100 /
11
#221
01
#222
b1101000 '
b01000 (
b0101110 )
b1101000 /
11
#223
01
#224
b1010001 '
b00111 (
b0101101 )
b1010001 /
11
#225
01
#226
b0100011 '
b00110 (
b0101100 )
b0100011 /
11
#227
01
#228
b1000110 '
b00101 (
b0101011 )
b1000110 /
11
#229
01
#230
b0001100 '
b00100 (
b0101010 )
b0001100 /
11
#231
01
#232
b0011001 '
b00011 (
b0101001 )
b0011001 /
11
#233
01
#234
b0110010 '
b00010 (
b0101000 )
b0110010 /
11
#235
01
#236
b1100100 '
b00001 (
b0100111 )
b1100100 /
11
#237
01
#238
b1001000 '
b00000 (
b0100110 )
b1001000 /
11
#239
01
#240
1%
b0010001 '
b01110 (
b0100101 )
1,
b00000000000000000000000000000111 .
b0010001 /
11
b00111111 5
#241
01
#242
0%
b0100010 '
b01101 (
b0100100 )
0,
b00000000000000000000000000000111 -
b0100010 /
11
#243
01
#244
b1000100 '
b01100 (
b0100011 )
b1000100 /
11
#245
01
#246
b0001000 '
b01011 (
b0100010 )
b0001000 /
11
#247
01
#248
b0010000 '
b01010 (
b0100001 )
b0010000 /
11
#249
01
#250
b0100000 '
b01001 (
b0100000 )
b0100000 /
11
#251
01
#252
b1000000 '
b01000 (
b0011111 )
b1000000 /
11
#253
01
#254
b0000001 '
b00111 (
b0011110 )
b0000001 /
11
#255
01
#256
b0000010 '
b00110 (
b0011101 )
b0000010 /
11
#257
01
#258
b0000100 '
b00101 (
b0011100 )
b0000100 /
11
#259
01
#260
b0001001 '
b00100 (
b0011011 )
b0001001 /
11
#261
01
#262
b0010010 '
b00011 (
b0011010 )
b0010010 /
11
#263
01
#264
b0100100 '
b00010 (
b0011001 )
b0100100 /
11
#265
01
#266
b1001001 '
b00001 (
b0011000 )
b1001001 /
11
#267
01
#268
b0010011 '
b00000 (
b0010111 )
b0010011 /
11
#269
01
#270
1%
b0100110 '
b01110 (
b0010110 )
1,
b00000000000000000000000000001000 .
b0100110 /
11
b01111111 5
#271
01
#272
1$
0%
b1001101 '
b01101 (
b0010101 )
b00000000000000000000000000000001 +
0,
b00000000000000000000000000001000 -
b1001101 /
11
#273
01
#274
b0011010 '
b01100 (
b1001100 )
b00000000000000000000000000000001 *
b0011010 /
11
#275
01
#276
b0110100 '
b01011 (
b0011001 )
b0110100 /
11
#277
01
#278
b1101001 '
b01010 (
b0110011 )
b1101001 /
11
#279
01
#280
b1010011 '
b01001 (
b1101000 )
b1010011 /
11
#281
01
#282
b0100111 '
b01000 (
b1010010 )
b0100111 /
11
#283
01
#284
b1001111 '
b00111 (
b0100110 )
b1001111 /
11
#285
01
#286
b0011110 '
b00110 (
b1001110 )
b0011110 /
11
#287
01
#288
b0111101 '
b00101 (
b0011101 )
b0111101 /
11
#289
01
#290
b1111011 '
b00100 (
b0111100 )
b1111011 /
11
#291
01
#292
b1110111 '
b00011 (
b1111010 )
b1110111 /
11
#293
01
#294
b1101110 '
b00010 (
b1110110 )
b1101110 /
11
#295
01
#296
b1011100 '
b00001 (
b1101101 )
b1011100 /
11
#297
01
#298
b0111000 '
b00000 (
b1011011 )
b0111000 /
11
#299
01
#300
1%
b1110000 '
b01110 (
b0110111 )
1,
b00000000000000000000000000000000 .
b1110000 /
11
b11111111 5
#301
01
#302
0#
0$
0%
b1100001 '
b01101 (
b1101111 )
0,
b00000000000000000000000000000000 -
b1100001 /
11
#303
01
#304
b1000011 '
b1101110 )
b1000011 /
11
#305
01
#306
b0000111 '
b1101101 )
b0000111 /
11
#307
01
#308
b0001111 '
b1101100 )
b0001111 /
11
#309
01
#310
b0011111 '
b1101011 )
b0011111 /
11
#311
01
#312
b0111111 '
b1101010 )
b0111111 /
11
#313
01
#314
b1111111 '
b1101001 )
b1111111 /
11
#315
01
#316
b1111110 '
b1101000 )
b1111110 /
11
#317
01
#318
b1111100 '
b1100111 )
b1111100 /
11
#319
01
#320
b1111000 '
b1100110 )
b1111000 /
11
#321
01
#322
b1110001 '
b1100101 )
b1110001 /
11
#323
01
#324
b1100011 '
b1100100 )
b1100011 /
11
#325
01
#326
b1000111 '
b1100011 )
b1000111 /
11
#327
01
#328
b0001110 '
b1100010 )
b0001110 /
11
#329
01
#330
b0011101 '
b1100001 )
b0011101 /
11
#331
01
#332
b0111011 '
b1100000 )
b0111011 /
11
#333
01
#334
b1110110 '
b1011111 )
b1110110 /
11
#335
01
#336
b1101100 '
b1011110 )
b1101100 /
11
#337
01
#338
b1011000 '
b1011101 )
b1011000 /
11
#339
01
#340
b0110001 '
b1011100 )
b0110001 /
11
#341
01
#342
b1100010 '
b1011011 )
b1100010 /
11
#343
01
#344
b1000101 '
b1011010 )
b1000101 /
11
#345
01
#346
b0001010 '
b1011001 )
b0001010 /
11
#347
01
#348
b0010100 '
b1011000 )
b0010100 /
11
#349
01
#350
b0101001 '
b1010111 )
b0101001 /
11
#351
01
#352
b1010010 '
b1010110 )
b1010010 /
11
#353
01
#354
b0100101 '
b1010101 )
b0100101 /
11
#355
01
#356
b1001011 '
b1010100 )
b1001011 /
11
#357
01
#358
b0010111 '
b1010011 )
b0010111 /
11
#359
01
#360
b0101111 '
b1010010 )
b0101111 /
11
#361
01
#362
b1011111 '
b1010001 )
b1011111 /
11
#363
01
#364
b0111110 '
b1010000 )
b0111110 /
11
#365
01
#366
b1111101 '
b1001111 )
b1111101 /
11
#367
01
#368
b1111010 '
b1001110 )
b1111010 /
11
#369
01
#370
b1110101 '
b1001101 )
b1110101 /
11
#371
01
#372
b1101010 '
b1001100 )
b1101010 /
11
#373
01
#374
b1010101 '
b1001011 )
b1010101 /
11
#375
01
#376
b0101010 '
b1001010 )
b0101010 /
11
#377
01
#378
b1010100 '
b1001001 )
b1010100 /
11
#379
01
#380
b0101000 '
b1001000 )
b0101000 /
11
#381
01
#382
b1010000 '
b1000111 )
b1010000 /
11
#383
01
#384
b0100001 '
b1000110 )
b0100001 /
11
#385
01
#386
b1000010 '
b1000101 )
b1000010 /
11
#387
01
#388
b0000101 '
b1000100 )
b0000101 /
11
#389
01
#390
b0001011 '
b1000011 )
b0001011 /
11
#391
01
#392
b0010110 '
b1000010 )
b0010110 /
11
#393
01
#394
b0101101 '
b1000001 )
b0101101 /
11
#395
01
#396
b1011011 '
b1000000 )
b1011011 /
11
#397
01
#398
b0110111 '
b0111111 )
b0110111 /
11
#399
01
#400
b1101111 '
b0111110 )
b1101111 /
11
#401
01
#402
b1011110 '
b0111101 )
b1011110 /
11
#403
01
#404
b0111100 '
b0111100 )
b0111100 /
11
#405
01
#406
b1111001 '
b0111011 )
b1111001 /
11
#407
01
#408
b1110011 '
b0111010 )
b1110011 /
11
#409
01
#410
b1100111 '
b0111001 )
b1100111 /
11
#411
01
#412
b1001110 '
b0111000 )
b1001110 /
11
#413
01
#414
b0011100 '
b0110111 )
b0011100 /
11
#415
01
#416
b0111001 '
b0110110 )
b0111001 /
11
#417
01
#418
b1110010 '
b0110101 )
b1110010 /
11
#419
01
#420
b1100101 '
b0110100 )
b1100101 /
11
#421
01
#422
b1001010 '
b0110011 )
b1001010 /
11
#423
01
#424
b0010101 '
b0110010 )
b0010101 /
11
#425
01
#426
b0101011 '
b0110001 )
b0101011 /
11
#427
01
#428
b1010110 '
b0110000 )
b1010110 /
11
#429
01
#430
b0101100 '
b0101111 )
b0101100 /
11
#431
01
#432
b1011001 '
b0101110 )
b1011001 /
11
#433
01
#434
b0110011 '
b0101101 )
b0110011 /
11
#435
01
#436
b1100110 '
b0101100 )
b1100110 /
11
#437
01
#438
b1001100 '
b0101011 )
b1001100 /
11
#439
01
#440
b0011000 '
b0101010 )
b0011000 /
11
#441
01
#442
b0110000 '
b0101001 )
b0110000 /
11
#443
01
#444
b1100000 '
b0101000 )
b1100000 /
11
#445
01
#446
b1000001 '
b0100111 )
b1000001 /
11
#447
01
#448
b0000011 '
b0100110 )
b0000011 /
11
#449
01
#450
b0000110 '
b0100101 )
b0000110 /
11
#451
01
#452
b0001101 '
b0100100 )
b0001101 /
11
#453
01
#454
b0011011 '
b0100011 )
b0011011 /
11
#455
01
#456
b0110110 '
b0100010 )
b0110110 /
11
#457
01
#458
b1101101 '
b0100001 )
b1101101 /
11
#459
01
#460
b1011010 '
b0100000 )
b1011010 /
11
#461
01
#462
b0110101 '
b0011111 )
b0110101 /
11
#463
01
#464
b1101011 '
b0011110 )
b1101011 /
11
#465
01
#466
b1010111 '
b0011101 )
b1010111 /
11
#467
01
#468
b0101110 '
b0011100 )
b0101110 /
11
#469
01
#470
b1011101 '
b0011011 )
b1011101 /
11
#471
01
#472
b0111010 '
b0011010 )
b0111010 /
11
#473
01
#474
b1110100 '
b0011001 )
b1110100 /
11
#475
01
#476
b1101000 '
b0011000 )
b1101000 /
11
#477
01
#478
b1010001 '
b0010111 )
b1010001 /
11
#479
01
#480
b0100011 '
b0010110 )
b0100011 /
11
#481
01
#482
b1000110 '
b0010101 )
b1000110 /
11
#483
01
#484
b0001100 '
b0010100 )
b0001100 /
11
#485
01
#486
b0011001 '
b0010011 )
b0011001 /
11
#487
01
#488
b0110010 '
b0010010 )
b0110010 /
11
#489
01
#490
b1100100 '
b0010001 )
b1100100 /
11
#491
01
#492
b1001000 '
b0010000 )
b1001000 /
11
#493
01
#494
b0010001 '
b0001111 )
b0010001 /
11
#495
01
#496
b0100010 '
b0001110 )
b0100010 /
11
#497
01
#498
b1000100 '
b0001101 )
b1000100 /
11
#499
01
#500
b0001000 '
b0001100 )
b0001000 /
11
#501
01
#502
b0010000 '
b0001011 )
b0010000 /
11
#503
01
#504
b0100000 '
b0001010 )
b0100000 /
11
#505
01
#506
b1000000 '
b0001001 )
b1000000 /
11
#507
01
#508
b0000001 '
b0001000 )
b0000001 /
11
#509
01
#510
b0000010 '
b0000111 )
b0000010 /
11
#511
01
#512
b0000100 '
b0000110 )
b0000100 /
11
#513
01
#514
b0001001 '
b0000101 )
b0001001 /
11
#515
01
#516
b0010010 '
b0000100 )
b0010010 /
11
#517
01
#518
b0100100 '
b0000011 )
b0100100 /
11
#519
01
#520
b1001001 '
b0000010 )
b1001001 /
11
#521
01
#522
b0010011 '
b0000001 )
b0010011 /
11
#523
01
#524
b0100110 '
b0000000 )
b00000000000000000000000000000010 +
b0100110 /
11
#525
01
#526
1&
b1001101 '
b0100101 )
b00000000000000000000000000000010 *
b00000000000000000000000000000000 +
1,
b00000000000000000000000000000001 .
b1001101 /
11
b00000000 5
#527
01
#528
0&
b0011010 '
b0100100 )
b00000000000000000000000000000000 *
0,
b0011010 /
11
#529
01
#530
b0110100 '
b0100011 )
b0110100 /
11
#531
01
#532
b1101001 '
b0100010 )
b1101001 /
11
#533
01
#534
b1010011 '
b0100001 )
b1010011 /
11
#535
01
#536
b0100111 '
b0100000 )
b0100111 /
11
#537
01
#538
b1001111 '
b0011111 )
b1001111 /
11
#539
01
#540
b0011110 '
b0011110 )
b0011110 /
11
#541
01
#542
b0111101 '
b0011101 )
b0111101 /
11
#543
01
#544
b1111011 '
b0011100 )
b1111011 /
11
#545
01
#546
b1110111 '
b0011011 )
b1110111 /
11
#547
01
#548
b1101110 '
b0011010 )
b1101110 /
11
#549
01
#550
b1011100 '
b0011001 )
b1011100 /
11
#551
01
#552
b0111000 '
b0011000 )
b0111000 /
11
#553
01
#554
b1110000 '
b0010111 )
b1110000 /
11
12
#555
01
#556
1#
b1100001 '
b0010110 )
b00000000000000000000000000000001 -
b1100001 /
11
02
#557
01
#558
b1000011 '
b01100 (
b0010101 )
b1000011 /
11
#559
01
#560
b0000111 '
b01011 (
b0010100 )
b0000111 /
11
#561
01
#562
b0001111 '
b01010 (
b0010011 )
b0001111 /
11
#563
01
#564
b0011111 '
b01001 (
b0010010 )
b0011111 /
11
#565
01
#566
b0111111 '
b01000 (
b0010001 )
b0111111 /
11
#567
01
#568
b1111111 '
b00111 (
b0010000 )
b1111111 /
11
#569
01
#570
b1111110 '
b00110 (
b0001111 )
b1111110 /
11
#571
01
#572
b1111100 '
b00101 (
b0001110 )
b1111100 /
11
#573
01
#574
b1111000 '
b00100 (
b0001101 )
b1111000 /
11
#575
01
#576
b1110001 '
b00011 (
b0001100 )
b1110001 /
11
#577
01
#578
b1100011 '
b00010 (
b0001011 )
b1100011 /
11
#579
01
#580
b1000111 '
b00001 (
b0001010 )
b1000111 /
11
#581
01
#582
b0001110 '
b00000 (
b0001001 )
b0001110 /
11
#583
01
#584
1%
b0011101 '
b01110 (
b0001000 )
1,
b00000000000000000000000000000010 .
b0011101 /
11
b00000001 5
#585
01
#586
0%
b0111011 '
b01101 (
b0000111 )
0,
b00000000000000000000000000000010 -
b0111011 /
11
#587
01
#588
b1110110 '
b01100 (
b0000110 )
b1110110 /
11
#589
01
#590
b1101100 '
b01011 (
b0000101 )
b1101100 /
11
#591
01
#592
b1011000 '
b01010 (
b0000100 )
b1011000 /
11
#593
01
#594
b0110001 '
b01001 (
b0000011 )
b0110001 /
11
#595
01
#596
b1100010 '
b01000 (
b0000010 )
b1100010 /
11
#597
01
#598
b1000101 '
b00111 (
b0000001 )
b1000101 /
11
#599
01
#600
b0001010 '
b00110 (
b0000000 )
b0001010 /
11
#601
01
#602
b0010100 '
b00101 (
b0001001 )
b0010100 /
11
#603
01
#604
b0101001 '
b00100 (
b0001000 )
b0101001 /
11
#605
01
#606
b1010010 '
b00011 (
b0000111 )
b1010010 /
11
#607
01
#608
b0100101 '
b00010 (
b0000110 )
b0100101 /
11
#609
01
#610
b1001011 '
b00001 (
b0000101 )
b1001011 /
11
#611
01
#612
b0010111 '
b00000 (
b0000100 )
b0010111 /
11
#613
01
#614
1%
b0101111 '
b01110 (
b0000011 )
1,
b00000000000000000000000000000011 .
b0101111 /
11
b00000011 5
#615
01
#616
0%
b1011111 '
b01101 (
b0000010 )
0,
b00000000000000000000000000000011 -
b1011111 /
11
#617
01
#618
b0111110 '
b01100 (
b0000001 )
b0111110 /
11
#619
01
#620
b1111101 '
b01011 (
b0000000 )
b1111101 /
11
#621
01
